<?xml version="1.0" standalone="yes" ?>
<?xml-stylesheet href="x2script.xsl" type="text/xsl" ?>
<script>
<name>plugin.sse.ui.ware.select.ship</name>
<version>2</version>
<engineversion>42</engineversion>
<description>SSE select new preferred ship for ware</description>
<arguments>
<argument index="1" name="ware" type="Var/All Wares" desc="ware" />
</arguments>
<sourcetext>
<line linenr="001" indent=""><var>$PageID&#160;=&#160;</var><text>get&#160;global&#160;variable:&#160;name=</text><var>'SSE.PageID'</var></line>
<line linenr="002" indent=""><text>load&#160;text:&#160;id=</text><var>$PageID</var></line>
<line linenr="003" indent=""></line>
<line linenr="004" indent=""><var>$Debug&#160;=&#160;</var><var>[FALSE]</var></line>
<line linenr="005" indent=""></line>
<line linenr="006" interruptable="@" indent=""><var>=&#160;</var><var>[THIS]&#160;-&gt;</var><text>&#160;call&#160;script&#160;</text><call>plugin.sse.consistency.check</call><text>&#160;:&#160;</text></line>
<line linenr="007" indent=""></line>
<line linenr="008" indent=""><text>gosub&#160;</text><var>load.settings</var></line>
<line linenr="009" indent=""></line>
<line linenr="010" indent=""><var>$menu.heading&#160;=&#160;</var><text>sprintf:&#160;pageid=</text><var>$PageID</var><text>&#160;textid=</text><var>1120</var><text>,&#160;</text><var>null</var><text>,&#160;</text><var>null</var><text>,&#160;</text><var>null</var><text>,&#160;</text><var>null</var><text>,&#160;</text><var>null</var></line>
<line linenr="011" indent=""><var>$menu.array&#160;=&#160;</var><text>&#160;create&#160;custom&#160;menu&#160;array:&#160;heading=</text><var>$menu.heading</var></line>
<line linenr="012" indent=""></line>
<line linenr="013" indent=""><comment><text>*&#160;</text><var>Any</var></comment></line>
<line linenr="014" indent=""><var>$menu.entry&#160;=&#160;</var><text>sprintf:&#160;pageid=</text><var>$PageID</var><text>&#160;textid=</text><var>1121</var><text>,&#160;</text><var>null</var><text>,&#160;</text><var>null</var><text>,&#160;</text><var>null</var><text>,&#160;</text><var>null</var><text>,&#160;</text><var>null</var></line>
<line linenr="015" indent=""><text>add&#160;custom&#160;menu&#160;item&#160;to&#160;array&#160;</text><var>$menu.array</var><text>:&#160;text=</text><var>$menu.entry</var><text>&#160;returnvalue=</text><var>'ANY'</var></line>
<line linenr="016" indent=""></line>
<line linenr="017" indent=""><comment><text>*&#160;</text><var>List&#160;of&#160;free&#160;ships</var></comment></line>
<line linenr="018" indent=""><var>$ships.count&#160;=&#160;</var><text>&#160;size&#160;of&#160;array&#160;</text><var>$settings.ships</var></line>
<line linenr="019" indent=""><var>$index&#160;=&#160;</var><var>0</var></line>
<line linenr="020" indent=""></line>
<line linenr="021" indent=""><var>while&#160;</var><var>$index</var><text>&#160;</text><var>&lt;</var><text>&#160;</text><var>$ships.count</var></line>
<line linenr="022" indent="&#160;"><var>$ship&#160;=&#160;</var><var>$settings.ships</var><text>[</text><var>$index</var><text>]</text></line>
<line linenr="023" indent="&#160;"><var>if&#160;</var><var>$ship</var></line>
<line linenr="024" indent="&#160;&#160;"></line>
<line linenr="025" indent="&#160;&#160;"><var>if&#160;not&#160;</var><text>&#160;find&#160;</text><var>$ship</var><text>&#160;in&#160;array:&#160;</text><var>$ware.ships</var></line>
<line linenr="026" indent="&#160;&#160;&#160;"></line>
<line linenr="027" indent="&#160;&#160;&#160;"><var>$ship.ID&#160;=&#160;</var><var>$ship&#160;-&gt;</var><text>&#160;get&#160;ID&#160;code</text></line>
<line linenr="028" indent="&#160;&#160;&#160;"></line>
<line linenr="029" indent="&#160;&#160;&#160;"><var>$ship.env&#160;=&#160;</var><var>$ship&#160;-&gt;</var><text>&#160;get&#160;environment</text></line>
<line linenr="030" indent="&#160;&#160;&#160;"><var>if&#160;</var><var>$ship.env</var><text>&#160;</text><var>!=</var><text>&#160;</text><var>[THIS]</var></line>
<line linenr="031" indent="&#160;&#160;&#160;&#160;"><var>$ship.away&#160;=&#160;</var><text>&#160;read&#160;text:&#160;page=</text><var>$PageID</var><text>&#160;id=</text><var>1123</var></line>
<line linenr="032" indent="&#160;&#160;&#160;&#160;"></line>
<line linenr="033" interruptable="@" indent="&#160;&#160;&#160;&#160;"><var>$menu.entry&#160;=&#160;</var><var>[THIS]&#160;-&gt;</var><text>&#160;call&#160;script&#160;</text><call>lib.chem.strings</call><text>&#160;:&#160;</text><text>&#160;Work&#160;Mode=</text><var>'sprintf'</var><text>&#160;</text><text>&#160;Arg1=</text><var>$PageID</var><text>&#160;</text><text>&#160;Arg2=</text><var>1122</var><text>&#160;</text><text>&#160;Arg3=</text><var>$ship</var><text>&#160;</text><text>&#160;Arg4=</text><var>$ship.ID</var><text>&#160;</text><text>&#160;Arg5=</text><var>$ship.away</var></line>
<line linenr="034" indent="&#160;&#160;&#160;&#160;"></line>
<line linenr="035" indent="&#160;&#160;&#160;"><text>else</text></line>
<line linenr="036" indent="&#160;&#160;&#160;&#160;"></line>
<line linenr="037" interruptable="@" indent="&#160;&#160;&#160;&#160;"><var>$menu.entry&#160;=&#160;</var><var>[THIS]&#160;-&gt;</var><text>&#160;call&#160;script&#160;</text><call>lib.chem.strings</call><text>&#160;:&#160;</text><text>&#160;Work&#160;Mode=</text><var>'sprintf'</var><text>&#160;</text><text>&#160;Arg1=</text><var>$PageID</var><text>&#160;</text><text>&#160;Arg2=</text><var>1122</var><text>&#160;</text><text>&#160;Arg3=</text><var>$ship</var><text>&#160;</text><text>&#160;Arg4=</text><var>$ship.ID</var><text>&#160;</text><text>&#160;Arg5=</text><var>'&#160;'</var></line>
<line linenr="038" indent="&#160;&#160;&#160;&#160;"></line>
<line linenr="039" indent="&#160;&#160;&#160;"><text>end</text></line>
<line linenr="040" indent="&#160;&#160;&#160;"><text>add&#160;custom&#160;menu&#160;item&#160;to&#160;array&#160;</text><var>$menu.array</var><text>:&#160;text=</text><var>$menu.entry</var><text>&#160;returnvalue=</text><var>$ship</var></line>
<line linenr="041" indent="&#160;&#160;&#160;"></line>
<line linenr="042" indent="&#160;&#160;"><text>end</text></line>
<line linenr="043" indent="&#160;&#160;"></line>
<line linenr="044" indent=""><comment><text>*&#160;</text><var>end&#160;if&#160;ship</var></comment></line>
<line linenr="045" indent="&#160;"><text>end</text></line>
<line linenr="046" indent="&#160;"><text>inc&#160;</text><var>$index&#160;=&#160;</var></line>
<line linenr="047" indent=""><comment><text>*&#160;</text><var>end&#160;while&#160;index</var></comment></line>
<line linenr="048" indent=""><text>end</text></line>
<line linenr="049" indent=""></line>
<line linenr="050" indent=""><var>$menu.select&#160;=&#160;</var><text>&#160;open&#160;custom&#160;menu:&#160;title=</text><var>$menu.heading</var><text>&#160;description=</text><var>null</var><text>&#160;option&#160;array=</text><var>$menu.array</var></line>
<line linenr="051" indent=""></line>
<line linenr="052" indent=""><var>skip&#160;if&#160;not&#160;</var><var>$Debug</var></line>
<line linenr="053" indent="&#160;"><text>write&#160;to&#160;player&#160;logbook:&#160;printf:&#160;fmt=</text><var>'Selected:&#160;%s'</var><text>,&#160;</text><var>$menu.select</var><text>,&#160;</text><var>null</var><text>,&#160;</text><var>null</var><text>,&#160;</text><var>null</var><text>,&#160;</text><var>null</var></line>
<line linenr="054" indent=""></line>
<line linenr="055" indent=""><var>if&#160;</var><var>$menu.select</var><text>&#160;</text><var>==</var><text>&#160;</text><var>'ANY'</var></line>
<line linenr="056" indent="&#160;"></line>
<line linenr="057" indent="&#160;"><var>skip&#160;if&#160;not&#160;</var><var>$Debug</var></line>
<line linenr="058" indent="&#160;&#160;"><text>write&#160;to&#160;player&#160;logbook:&#160;printf:&#160;fmt=</text><var>'All&#160;Ships&#160;deleted'</var><text>,&#160;</text><var>$menu.select</var><text>,&#160;</text><var>null</var><text>,&#160;</text><var>null</var><text>,&#160;</text><var>null</var><text>,&#160;</text><var>null</var></line>
<line linenr="059" indent="&#160;"></line>
<line linenr="060" indent="&#160;"><var>$ware.ships&#160;=&#160;</var><text>&#160;array&#160;alloc:&#160;size=</text><var>0</var></line>
<line linenr="061" indent="&#160;"><text>gosub&#160;</text><var>save.settings</var></line>
<line linenr="062" indent="&#160;"></line>
<line linenr="063" indent=""><var>else&#160;if&#160;</var><text>&#160;is&#160;datatyp[&#160;</text><var>$menu.select</var><text>&#160;]&#160;==&#160;</text><var>DATATYP_SHIP</var></line>
<line linenr="064" indent="&#160;"></line>
<line linenr="065" indent="&#160;"><text>append&#160;</text><var>$menu.select</var><text>&#160;to&#160;array&#160;</text><var>$ware.ships</var></line>
<line linenr="066" indent="&#160;"></line>
<line linenr="067" indent="&#160;"><var>$new.length&#160;=&#160;</var><text>&#160;size&#160;of&#160;array&#160;</text><var>$ware.ships</var></line>
<line linenr="068" indent="&#160;"></line>
<line linenr="069" indent="&#160;"><var>skip&#160;if&#160;not&#160;</var><var>$Debug</var></line>
<line linenr="070" indent="&#160;&#160;"><text>write&#160;to&#160;player&#160;logbook:&#160;printf:&#160;fmt=</text><var>'New&#160;length&#160;of&#160;array:&#160;%s'</var><text>,&#160;</text><var>$new.length</var><text>,&#160;</text><var>null</var><text>,&#160;</text><var>null</var><text>,&#160;</text><var>null</var><text>,&#160;</text><var>null</var></line>
<line linenr="071" indent="&#160;"></line>
<line linenr="072" indent="&#160;"><text>gosub&#160;</text><var>save.settings</var></line>
<line linenr="073" indent="&#160;"></line>
<line linenr="074" indent=""><text>end</text></line>
<line linenr="075" indent=""></line>
<line linenr="076" indent=""><text>return&#160;</text><var>null</var></line>
<line linenr="077" indent=""></line>
<line linenr="078" indent=""><comment><text>*&#160;</text><var>--------------------------------------------------------------------------------</var></comment></line>
<line linenr="079" indent=""><var>load.settings</var><text>:</text></line>
<line linenr="080" indent=""></line>
<line linenr="081" indent=""><var>$settings&#160;=&#160;</var><var>[THIS]&#160;-&gt;</var><text>&#160;get&#160;local&#160;variable:&#160;name=</text><var>'sse.settings'</var></line>
<line linenr="082" indent=""><var>$settings.wares&#160;=&#160;</var><var>$settings</var><text>[</text><var>2</var><text>]</text></line>
<line linenr="083" indent=""><var>$settings.ships&#160;=&#160;</var><var>$settings</var><text>[</text><var>3</var><text>]</text></line>
<line linenr="084" indent=""></line>
<line linenr="085" indent=""><comment><text>*&#160;</text><var>Find&#160;the&#160;ware</var></comment></line>
<line linenr="086" indent=""><var>$ware.count&#160;=&#160;</var><text>&#160;size&#160;of&#160;array&#160;</text><var>$settings.wares</var></line>
<line linenr="087" indent=""><var>$index&#160;=&#160;</var><var>0</var></line>
<line linenr="088" indent=""></line>
<line linenr="089" indent=""><var>while&#160;</var><var>$index</var><text>&#160;</text><var>&lt;</var><text>&#160;</text><var>$ware.count</var></line>
<line linenr="090" indent="&#160;"></line>
<line linenr="091" indent="&#160;"><var>$ware.props&#160;=&#160;</var><var>$settings.wares</var><text>[</text><var>$index</var><text>]</text></line>
<line linenr="092" indent="&#160;"></line>
<line linenr="093" indent="&#160;"><var>if&#160;</var><var>$ware.props</var></line>
<line linenr="094" indent="&#160;&#160;"><var>$ware.name&#160;=&#160;</var><var>$ware.props</var><text>[</text><var>0</var><text>]</text></line>
<line linenr="095" indent="&#160;&#160;"></line>
<line linenr="096" indent="&#160;&#160;"><var>if&#160;</var><var>$ware.name</var><text>&#160;</text><var>==</var><text>&#160;</text><var>$ware</var></line>
<line linenr="097" indent="&#160;&#160;&#160;"><var>$ware.ships&#160;=&#160;</var><var>$ware.props</var><text>[</text><var>3</var><text>]</text></line>
<line linenr="098" indent="&#160;&#160;&#160;"><var>$ware.index&#160;=&#160;</var><var>$index</var></line>
<line linenr="099" indent="&#160;&#160;&#160;"><text>break</text></line>
<line linenr="100" indent="&#160;&#160;"><text>end</text></line>
<line linenr="101" indent="&#160;&#160;"></line>
<line linenr="102" indent=""><comment><text>*&#160;</text><var>end&#160;if&#160;ware.props</var></comment></line>
<line linenr="103" indent="&#160;"><text>end</text></line>
<line linenr="104" indent="&#160;"></line>
<line linenr="105" indent="&#160;"><text>inc&#160;</text><var>$index&#160;=&#160;</var></line>
<line linenr="106" indent=""><comment><text>*&#160;</text><var>end&#160;while&#160;index</var></comment></line>
<line linenr="107" indent=""><text>end</text></line>
<line linenr="108" indent=""></line>
<line linenr="109" indent=""><text>endsub</text></line>
<line linenr="110" indent=""></line>
<line linenr="111" indent=""><comment><text>*&#160;</text><var>--------------------------------------------------------------------------------</var></comment></line>
<line linenr="112" indent=""><var>save.settings</var><text>:</text></line>
<line linenr="113" indent=""></line>
<line linenr="114" indent=""><var>$ware.props</var><text>[</text><var>3</var><text>]&#160;=&#160;</text><var>$ware.ships</var></line>
<line linenr="115" indent=""><var>$settings.wares</var><text>[</text><var>$ware.index</var><text>]&#160;=&#160;</text><var>$ware.props</var></line>
<line linenr="116" indent=""><var>$settings</var><text>[</text><var>2</var><text>]&#160;=&#160;</text><var>$settings.wares</var></line>
<line linenr="117" indent=""><var>[THIS]&#160;-&gt;</var><text>&#160;set&#160;local&#160;variable:&#160;name=</text><var>'sse.settings'</var><text>&#160;value=</text><var>$settings</var></line>
<line linenr="118" indent=""></line>
<line linenr="119" indent=""><var>skip&#160;if&#160;not&#160;</var><var>$Debug</var></line>
<line linenr="120" indent="&#160;"><text>write&#160;to&#160;player&#160;logbook:&#160;printf:&#160;fmt=</text><var>'Successfully&#160;saved'</var><text>,&#160;</text><var>null</var><text>,&#160;</text><var>null</var><text>,&#160;</text><var>null</var><text>,&#160;</text><var>null</var><text>,&#160;</text><var>null</var></line>
<line linenr="121" indent=""></line>
<line linenr="122" indent=""><text>endsub</text></line>
<line linenr="123" indent=""><text>return&#160;</text><var>null</var></line>
</sourcetext>
<codearray>

<sval type="array" size="10">
  <sval type="string" val="plugin.sse.ui.ware.select.ship"/>
  <sval type="int" val="42"/>
  <sval type="string" val="SSE select new preferred ship for ware"/>
  <sval type="int" val="2"/>
  <sval type="int" val="0"/>
  <sval type="array" size="22">
    <sval type="string" val="ware"/>
    <sval type="string" val="PageID"/>
    <sval type="string" val="Debug"/>
    <sval type="string" val="menu.heading"/>
    <sval type="string" val="menu.array"/>
    <sval type="string" val="menu.entry"/>
    <sval type="string" val="ships.count"/>
    <sval type="string" val="settings.ships"/>
    <sval type="string" val="index"/>
    <sval type="string" val="ship"/>
    <sval type="string" val="ware.ships"/>
    <sval type="string" val="ship.ID"/>
    <sval type="string" val="ship.env"/>
    <sval type="string" val="ship.away"/>
    <sval type="string" val="menu.select"/>
    <sval type="string" val="new.length"/>
    <sval type="string" val="settings"/>
    <sval type="string" val="settings.wares"/>
    <sval type="string" val="ware.count"/>
    <sval type="string" val="ware.props"/>
    <sval type="string" val="ware.name"/>
    <sval type="string" val="ware.index"/>
  </sval>
  <sval type="array" size="67">
    <sval type="array" size="4">
      <sval type="int" val="158"/>
      <sval type="int" val="5"/>
      <sval type="string" val="SSE.PageID"/>
      <sval type="int" val="1"/>
    </sval>
    <sval type="array" size="3">
      <sval type="int" val="151"/>
      <sval type="int" val="131074"/>
      <sval type="int" val="1"/>
    </sval>
    <sval type="array" size="7">
      <sval type="int" val="104"/>
      <sval type="int" val="2"/>
      <sval type="int" val="1"/>
      <sval type="int" val="131075"/>
      <sval type="int" val="9"/>
      <sval type="int" val="1"/>
      <sval type="int" val="-1"/>
    </sval>
    <sval type="array" size="6">
      <sval type="int" val="102"/>
      <sval type="string" val="plugin.sse.consistency.check"/>
      <sval type="int" val="-2147483647"/>
      <sval type="int" val="131075"/>
      <sval type="int" val="1"/>
      <sval type="int" val="0"/>
    </sval>
    <sval type="array" size="2">
      <sval type="int" val="1167"/>
      <sval type="int" val="41"/>
    </sval>
    <sval type="array" size="16">
      <sval type="int" val="150"/>
      <sval type="int" val="3"/>
      <sval type="int" val="131074"/>
      <sval type="int" val="1"/>
      <sval type="int" val="4"/>
      <sval type="int" val="1120"/>
      <sval type="int" val="0"/>
      <sval type="int" val="0"/>
      <sval type="int" val="0"/>
      <sval type="int" val="0"/>
      <sval type="int" val="0"/>
      <sval type="int" val="0"/>
      <sval type="int" val="0"/>
      <sval type="int" val="0"/>
      <sval type="int" val="0"/>
      <sval type="int" val="0"/>
    </sval>
    <sval type="array" size="4">
      <sval type="int" val="1416"/>
      <sval type="int" val="4"/>
      <sval type="int" val="131074"/>
      <sval type="int" val="3"/>
    </sval>
    <sval type="array" size="16">
      <sval type="int" val="150"/>
      <sval type="int" val="5"/>
      <sval type="int" val="131074"/>
      <sval type="int" val="1"/>
      <sval type="int" val="4"/>
      <sval type="int" val="1121"/>
      <sval type="int" val="0"/>
      <sval type="int" val="0"/>
      <sval type="int" val="0"/>
      <sval type="int" val="0"/>
      <sval type="int" val="0"/>
      <sval type="int" val="0"/>
      <sval type="int" val="0"/>
      <sval type="int" val="0"/>
      <sval type="int" val="0"/>
      <sval type="int" val="0"/>
    </sval>
    <sval type="array" size="7">
      <sval type="int" val="1447"/>
      <sval type="int" val="131074"/>
      <sval type="int" val="4"/>
      <sval type="int" val="131074"/>
      <sval type="int" val="5"/>
      <sval type="int" val="5"/>
      <sval type="string" val="ANY"/>
    </sval>
    <sval type="array" size="4">
      <sval type="int" val="131"/>
      <sval type="int" val="6"/>
      <sval type="int" val="131074"/>
      <sval type="int" val="7"/>
    </sval>
    <sval type="array" size="7">
      <sval type="int" val="104"/>
      <sval type="int" val="8"/>
      <sval type="int" val="1"/>
      <sval type="int" val="4"/>
      <sval type="int" val="0"/>
      <sval type="int" val="1"/>
      <sval type="int" val="-1"/>
    </sval>
    <sval type="array" size="13">
      <sval type="int" val="104"/>
      <sval type="int" val="-1610606327"/>
      <sval type="int" val="3"/>
      <sval type="int" val="131074"/>
      <sval type="int" val="8"/>
      <sval type="int" val="131074"/>
      <sval type="int" val="6"/>
      <sval type="int" val="15"/>
      <sval type="int" val="3"/>
      <sval type="int" val="3"/>
      <sval type="int" val="-1"/>
      <sval type="int" val="3"/>
      <sval type="int" val="-2"/>
    </sval>
    <sval type="array" size="6">
      <sval type="int" val="129"/>
      <sval type="int" val="9"/>
      <sval type="int" val="131074"/>
      <sval type="int" val="7"/>
      <sval type="int" val="131074"/>
      <sval type="int" val="8"/>
    </sval>
    <sval type="array" size="7">
      <sval type="int" val="104"/>
      <sval type="int" val="-1610606845"/>
      <sval type="int" val="1"/>
      <sval type="int" val="131074"/>
      <sval type="int" val="9"/>
      <sval type="int" val="1"/>
      <sval type="int" val="-1"/>
    </sval>
    <sval type="array" size="6">
      <sval type="int" val="1406"/>
      <sval type="int" val="-536865020"/>
      <sval type="int" val="131074"/>
      <sval type="int" val="9"/>
      <sval type="int" val="131074"/>
      <sval type="int" val="10"/>
    </sval>
    <sval type="array" size="4">
      <sval type="int" val="1036"/>
      <sval type="int" val="131074"/>
      <sval type="int" val="9"/>
      <sval type="int" val="11"/>
    </sval>
    <sval type="array" size="4">
      <sval type="int" val="702"/>
      <sval type="int" val="131074"/>
      <sval type="int" val="9"/>
      <sval type="int" val="12"/>
    </sval>
    <sval type="array" size="13">
      <sval type="int" val="104"/>
      <sval type="int" val="-1610607357"/>
      <sval type="int" val="3"/>
      <sval type="int" val="131074"/>
      <sval type="int" val="12"/>
      <sval type="int" val="131075"/>
      <sval type="int" val="1"/>
      <sval type="int" val="15"/>
      <sval type="int" val="1"/>
      <sval type="int" val="3"/>
      <sval type="int" val="-1"/>
      <sval type="int" val="1"/>
      <sval type="int" val="-2"/>
    </sval>
    <sval type="array" size="6">
      <sval type="int" val="126"/>
      <sval type="int" val="13"/>
      <sval type="int" val="131074"/>
      <sval type="int" val="1"/>
      <sval type="int" val="4"/>
      <sval type="int" val="1123"/>
    </sval>
    <sval type="array" size="18">
      <sval type="int" val="102"/>
      <sval type="string" val="lib.chem.strings"/>
      <sval type="int" val="5"/>
      <sval type="int" val="131075"/>
      <sval type="int" val="1"/>
      <sval type="int" val="6"/>
      <sval type="int" val="5"/>
      <sval type="string" val="sprintf"/>
      <sval type="int" val="131074"/>
      <sval type="int" val="1"/>
      <sval type="int" val="4"/>
      <sval type="int" val="1122"/>
      <sval type="int" val="131074"/>
      <sval type="int" val="9"/>
      <sval type="int" val="131074"/>
      <sval type="int" val="11"/>
      <sval type="int" val="131074"/>
      <sval type="int" val="13"/>
    </sval>
    <sval type="array" size="2">
      <sval type="int" val="112"/>
      <sval type="int" val="22"/>
    </sval>
    <sval type="array" size="18">
      <sval type="int" val="102"/>
      <sval type="string" val="lib.chem.strings"/>
      <sval type="int" val="5"/>
      <sval type="int" val="131075"/>
      <sval type="int" val="1"/>
      <sval type="int" val="6"/>
      <sval type="int" val="5"/>
      <sval type="string" val="sprintf"/>
      <sval type="int" val="131074"/>
      <sval type="int" val="1"/>
      <sval type="int" val="4"/>
      <sval type="int" val="1122"/>
      <sval type="int" val="131074"/>
      <sval type="int" val="9"/>
      <sval type="int" val="131074"/>
      <sval type="int" val="11"/>
      <sval type="int" val="5"/>
      <sval type="string" val=" "/>
    </sval>
    <sval type="array" size="7">
      <sval type="int" val="1447"/>
      <sval type="int" val="131074"/>
      <sval type="int" val="4"/>
      <sval type="int" val="131074"/>
      <sval type="int" val="5"/>
      <sval type="int" val="131074"/>
      <sval type="int" val="9"/>
    </sval>
    <sval type="array" size="2">
      <sval type="int" val="142"/>
      <sval type="int" val="8"/>
    </sval>
    <sval type="array" size="2">
      <sval type="int" val="112"/>
      <sval type="int" val="11"/>
    </sval>
    <sval type="array" size="8">
      <sval type="int" val="1230"/>
      <sval type="int" val="14"/>
      <sval type="int" val="131074"/>
      <sval type="int" val="3"/>
      <sval type="int" val="0"/>
      <sval type="int" val="0"/>
      <sval type="int" val="131074"/>
      <sval type="int" val="4"/>
    </sval>
    <sval type="array" size="7">
      <sval type="int" val="104"/>
      <sval type="int" val="-1610605560"/>
      <sval type="int" val="1"/>
      <sval type="int" val="131074"/>
      <sval type="int" val="2"/>
      <sval type="int" val="1"/>
      <sval type="int" val="-1"/>
    </sval>
    <sval type="array" size="13">
      <sval type="int" val="402"/>
      <sval type="int" val="5"/>
      <sval type="string" val="Selected: %s"/>
      <sval type="int" val="131074"/>
      <sval type="int" val="14"/>
      <sval type="int" val="0"/>
      <sval type="int" val="0"/>
      <sval type="int" val="0"/>
      <sval type="int" val="0"/>
      <sval type="int" val="0"/>
      <sval type="int" val="0"/>
      <sval type="int" val="0"/>
      <sval type="int" val="0"/>
    </sval>
    <sval type="array" size="13">
      <sval type="int" val="104"/>
      <sval type="int" val="-1610604029"/>
      <sval type="int" val="3"/>
      <sval type="int" val="131074"/>
      <sval type="int" val="14"/>
      <sval type="int" val="5"/>
      <sval type="string" val="ANY"/>
      <sval type="int" val="15"/>
      <sval type="int" val="0"/>
      <sval type="int" val="3"/>
      <sval type="int" val="-1"/>
      <sval type="int" val="0"/>
      <sval type="int" val="-2"/>
    </sval>
    <sval type="array" size="7">
      <sval type="int" val="104"/>
      <sval type="int" val="-1610604792"/>
      <sval type="int" val="1"/>
      <sval type="int" val="131074"/>
      <sval type="int" val="2"/>
      <sval type="int" val="1"/>
      <sval type="int" val="-1"/>
    </sval>
    <sval type="array" size="13">
      <sval type="int" val="402"/>
      <sval type="int" val="5"/>
      <sval type="string" val="All Ships deleted"/>
      <sval type="int" val="131074"/>
      <sval type="int" val="14"/>
      <sval type="int" val="0"/>
      <sval type="int" val="0"/>
      <sval type="int" val="0"/>
      <sval type="int" val="0"/>
      <sval type="int" val="0"/>
      <sval type="int" val="0"/>
      <sval type="int" val="0"/>
      <sval type="int" val="0"/>
    </sval>
    <sval type="array" size="4">
      <sval type="int" val="128"/>
      <sval type="int" val="10"/>
      <sval type="int" val="4"/>
      <sval type="int" val="0"/>
    </sval>
    <sval type="array" size="2">
      <sval type="int" val="1167"/>
      <sval type="int" val="58"/>
    </sval>
    <sval type="array" size="2">
      <sval type="int" val="112"/>
      <sval type="int" val="40"/>
    </sval>
    <sval type="array" size="6">
      <sval type="int" val="125"/>
      <sval type="int" val="-1610602491"/>
      <sval type="int" val="131074"/>
      <sval type="int" val="14"/>
      <sval type="int" val="20"/>
      <sval type="int" val="65542"/>
    </sval>
    <sval type="array" size="5">
      <sval type="int" val="135"/>
      <sval type="int" val="131074"/>
      <sval type="int" val="10"/>
      <sval type="int" val="131074"/>
      <sval type="int" val="14"/>
    </sval>
    <sval type="array" size="4">
      <sval type="int" val="131"/>
      <sval type="int" val="15"/>
      <sval type="int" val="131074"/>
      <sval type="int" val="10"/>
    </sval>
    <sval type="array" size="7">
      <sval type="int" val="104"/>
      <sval type="int" val="-1610602744"/>
      <sval type="int" val="1"/>
      <sval type="int" val="131074"/>
      <sval type="int" val="2"/>
      <sval type="int" val="1"/>
      <sval type="int" val="-1"/>
    </sval>
    <sval type="array" size="13">
      <sval type="int" val="402"/>
      <sval type="int" val="5"/>
      <sval type="string" val="New length of array: %s"/>
      <sval type="int" val="131074"/>
      <sval type="int" val="15"/>
      <sval type="int" val="0"/>
      <sval type="int" val="0"/>
      <sval type="int" val="0"/>
      <sval type="int" val="0"/>
      <sval type="int" val="0"/>
      <sval type="int" val="0"/>
      <sval type="int" val="0"/>
      <sval type="int" val="0"/>
    </sval>
    <sval type="array" size="2">
      <sval type="int" val="1167"/>
      <sval type="int" val="58"/>
    </sval>
    <sval type="array" size="3">
      <sval type="int" val="103"/>
      <sval type="int" val="0"/>
      <sval type="int" val="0"/>
    </sval>
    <sval type="array" size="2">
      <sval type="int" val="101"/>
      <sval type="string" val="load.settings"/>
    </sval>
    <sval type="array" size="6">
      <sval type="int" val="156"/>
      <sval type="int" val="131075"/>
      <sval type="int" val="1"/>
      <sval type="int" val="5"/>
      <sval type="string" val="sse.settings"/>
      <sval type="int" val="16"/>
    </sval>
    <sval type="array" size="6">
      <sval type="int" val="129"/>
      <sval type="int" val="17"/>
      <sval type="int" val="131074"/>
      <sval type="int" val="16"/>
      <sval type="int" val="4"/>
      <sval type="int" val="2"/>
    </sval>
    <sval type="array" size="6">
      <sval type="int" val="129"/>
      <sval type="int" val="7"/>
      <sval type="int" val="131074"/>
      <sval type="int" val="16"/>
      <sval type="int" val="4"/>
      <sval type="int" val="3"/>
    </sval>
    <sval type="array" size="4">
      <sval type="int" val="131"/>
      <sval type="int" val="18"/>
      <sval type="int" val="131074"/>
      <sval type="int" val="17"/>
    </sval>
    <sval type="array" size="7">
      <sval type="int" val="104"/>
      <sval type="int" val="8"/>
      <sval type="int" val="1"/>
      <sval type="int" val="4"/>
      <sval type="int" val="0"/>
      <sval type="int" val="1"/>
      <sval type="int" val="-1"/>
    </sval>
    <sval type="array" size="13">
      <sval type="int" val="104"/>
      <sval type="int" val="-1610598135"/>
      <sval type="int" val="3"/>
      <sval type="int" val="131074"/>
      <sval type="int" val="8"/>
      <sval type="int" val="131074"/>
      <sval type="int" val="18"/>
      <sval type="int" val="15"/>
      <sval type="int" val="3"/>
      <sval type="int" val="3"/>
      <sval type="int" val="-1"/>
      <sval type="int" val="3"/>
      <sval type="int" val="-2"/>
    </sval>
    <sval type="array" size="6">
      <sval type="int" val="129"/>
      <sval type="int" val="19"/>
      <sval type="int" val="131074"/>
      <sval type="int" val="17"/>
      <sval type="int" val="131074"/>
      <sval type="int" val="8"/>
    </sval>
    <sval type="array" size="7">
      <sval type="int" val="104"/>
      <sval type="int" val="-1610598653"/>
      <sval type="int" val="1"/>
      <sval type="int" val="131074"/>
      <sval type="int" val="19"/>
      <sval type="int" val="1"/>
      <sval type="int" val="-1"/>
    </sval>
    <sval type="array" size="6">
      <sval type="int" val="129"/>
      <sval type="int" val="20"/>
      <sval type="int" val="131074"/>
      <sval type="int" val="19"/>
      <sval type="int" val="4"/>
      <sval type="int" val="0"/>
    </sval>
    <sval type="array" size="13">
      <sval type="int" val="104"/>
      <sval type="int" val="-1610598653"/>
      <sval type="int" val="3"/>
      <sval type="int" val="131074"/>
      <sval type="int" val="20"/>
      <sval type="int" val="131074"/>
      <sval type="int" val="0"/>
      <sval type="int" val="15"/>
      <sval type="int" val="0"/>
      <sval type="int" val="3"/>
      <sval type="int" val="-1"/>
      <sval type="int" val="0"/>
      <sval type="int" val="-2"/>
    </sval>
    <sval type="array" size="6">
      <sval type="int" val="129"/>
      <sval type="int" val="10"/>
      <sval type="int" val="131074"/>
      <sval type="int" val="19"/>
      <sval type="int" val="4"/>
      <sval type="int" val="3"/>
    </sval>
    <sval type="array" size="7">
      <sval type="int" val="104"/>
      <sval type="int" val="21"/>
      <sval type="int" val="1"/>
      <sval type="int" val="131074"/>
      <sval type="int" val="8"/>
      <sval type="int" val="1"/>
      <sval type="int" val="-1"/>
    </sval>
    <sval type="array" size="2">
      <sval type="int" val="112"/>
      <sval type="int" val="57"/>
    </sval>
    <sval type="array" size="2">
      <sval type="int" val="142"/>
      <sval type="int" val="8"/>
    </sval>
    <sval type="array" size="2">
      <sval type="int" val="112"/>
      <sval type="int" val="47"/>
    </sval>
    <sval type="array" size="1">
      <sval type="int" val="1168"/>
    </sval>
    <sval type="array" size="2">
      <sval type="int" val="101"/>
      <sval type="string" val="save.settings"/>
    </sval>
    <sval type="array" size="7">
      <sval type="int" val="130"/>
      <sval type="int" val="131074"/>
      <sval type="int" val="19"/>
      <sval type="int" val="4"/>
      <sval type="int" val="3"/>
      <sval type="int" val="131074"/>
      <sval type="int" val="10"/>
    </sval>
    <sval type="array" size="7">
      <sval type="int" val="130"/>
      <sval type="int" val="131074"/>
      <sval type="int" val="17"/>
      <sval type="int" val="131074"/>
      <sval type="int" val="21"/>
      <sval type="int" val="131074"/>
      <sval type="int" val="19"/>
    </sval>
    <sval type="array" size="7">
      <sval type="int" val="130"/>
      <sval type="int" val="131074"/>
      <sval type="int" val="16"/>
      <sval type="int" val="4"/>
      <sval type="int" val="2"/>
      <sval type="int" val="131074"/>
      <sval type="int" val="17"/>
    </sval>
    <sval type="array" size="7">
      <sval type="int" val="155"/>
      <sval type="int" val="131075"/>
      <sval type="int" val="1"/>
      <sval type="int" val="5"/>
      <sval type="string" val="sse.settings"/>
      <sval type="int" val="131074"/>
      <sval type="int" val="16"/>
    </sval>
    <sval type="array" size="7">
      <sval type="int" val="104"/>
      <sval type="int" val="-1610596088"/>
      <sval type="int" val="1"/>
      <sval type="int" val="131074"/>
      <sval type="int" val="2"/>
      <sval type="int" val="1"/>
      <sval type="int" val="-1"/>
    </sval>
    <sval type="array" size="13">
      <sval type="int" val="402"/>
      <sval type="int" val="5"/>
      <sval type="string" val="Successfully saved"/>
      <sval type="int" val="0"/>
      <sval type="int" val="0"/>
      <sval type="int" val="0"/>
      <sval type="int" val="0"/>
      <sval type="int" val="0"/>
      <sval type="int" val="0"/>
      <sval type="int" val="0"/>
      <sval type="int" val="0"/>
      <sval type="int" val="0"/>
      <sval type="int" val="0"/>
    </sval>
    <sval type="array" size="1">
      <sval type="int" val="1168"/>
    </sval>
    <sval type="array" size="3">
      <sval type="int" val="103"/>
      <sval type="int" val="0"/>
      <sval type="int" val="0"/>
    </sval>
  </sval>
  <sval type="array" size="1">
    <sval type="array" size="2">
      <sval type="int" val="42"/>
      <sval type="string" val="ware"/>
    </sval>
  </sval>
  <sval type="array" size="61">
    <sval type="array" size="2">
      <sval type="int" val="2"/>
      <sval type="int" val="2"/>
    </sval>
    <sval type="array" size="2">
      <sval type="int" val="3"/>
      <sval type="int" val="2"/>
    </sval>
    <sval type="array" size="2">
      <sval type="int" val="4"/>
      <sval type="int" val="2"/>
    </sval>
    <sval type="array" size="2">
      <sval type="int" val="5"/>
      <sval type="int" val="2"/>
    </sval>
    <sval type="array" size="2">
      <sval type="int" val="7"/>
      <sval type="int" val="2"/>
    </sval>
    <sval type="array" size="3">
      <sval type="int" val="7"/>
      <sval type="int" val="1"/>
      <sval type="string" val="Any"/>
    </sval>
    <sval type="array" size="2">
      <sval type="int" val="9"/>
      <sval type="int" val="2"/>
    </sval>
    <sval type="array" size="3">
      <sval type="int" val="9"/>
      <sval type="int" val="1"/>
      <sval type="string" val="List of free ships"/>
    </sval>
    <sval type="array" size="2">
      <sval type="int" val="11"/>
      <sval type="int" val="2"/>
    </sval>
    <sval type="array" size="2">
      <sval type="int" val="14"/>
      <sval type="int" val="2"/>
    </sval>
    <sval type="array" size="2">
      <sval type="int" val="15"/>
      <sval type="int" val="2"/>
    </sval>
    <sval type="array" size="2">
      <sval type="int" val="16"/>
      <sval type="int" val="2"/>
    </sval>
    <sval type="array" size="2">
      <sval type="int" val="19"/>
      <sval type="int" val="2"/>
    </sval>
    <sval type="array" size="2">
      <sval type="int" val="20"/>
      <sval type="int" val="2"/>
    </sval>
    <sval type="array" size="2">
      <sval type="int" val="21"/>
      <sval type="int" val="5"/>
    </sval>
    <sval type="array" size="2">
      <sval type="int" val="21"/>
      <sval type="int" val="2"/>
    </sval>
    <sval type="array" size="2">
      <sval type="int" val="22"/>
      <sval type="int" val="2"/>
    </sval>
    <sval type="array" size="2">
      <sval type="int" val="22"/>
      <sval type="int" val="4"/>
    </sval>
    <sval type="array" size="2">
      <sval type="int" val="23"/>
      <sval type="int" val="2"/>
    </sval>
    <sval type="array" size="2">
      <sval type="int" val="23"/>
      <sval type="int" val="4"/>
    </sval>
    <sval type="array" size="2">
      <sval type="int" val="23"/>
      <sval type="int" val="2"/>
    </sval>
    <sval type="array" size="3">
      <sval type="int" val="23"/>
      <sval type="int" val="1"/>
      <sval type="string" val="end if ship"/>
    </sval>
    <sval type="array" size="2">
      <sval type="int" val="23"/>
      <sval type="int" val="4"/>
    </sval>
    <sval type="array" size="3">
      <sval type="int" val="24"/>
      <sval type="int" val="1"/>
      <sval type="string" val="end while index"/>
    </sval>
    <sval type="array" size="2">
      <sval type="int" val="25"/>
      <sval type="int" val="4"/>
    </sval>
    <sval type="array" size="2">
      <sval type="int" val="25"/>
      <sval type="int" val="2"/>
    </sval>
    <sval type="array" size="2">
      <sval type="int" val="26"/>
      <sval type="int" val="2"/>
    </sval>
    <sval type="array" size="2">
      <sval type="int" val="28"/>
      <sval type="int" val="2"/>
    </sval>
    <sval type="array" size="2">
      <sval type="int" val="29"/>
      <sval type="int" val="2"/>
    </sval>
    <sval type="array" size="2">
      <sval type="int" val="31"/>
      <sval type="int" val="2"/>
    </sval>
    <sval type="array" size="2">
      <sval type="int" val="33"/>
      <sval type="int" val="2"/>
    </sval>
    <sval type="array" size="2">
      <sval type="int" val="35"/>
      <sval type="int" val="2"/>
    </sval>
    <sval type="array" size="2">
      <sval type="int" val="36"/>
      <sval type="int" val="2"/>
    </sval>
    <sval type="array" size="2">
      <sval type="int" val="37"/>
      <sval type="int" val="2"/>
    </sval>
    <sval type="array" size="2">
      <sval type="int" val="39"/>
      <sval type="int" val="2"/>
    </sval>
    <sval type="array" size="2">
      <sval type="int" val="40"/>
      <sval type="int" val="2"/>
    </sval>
    <sval type="array" size="2">
      <sval type="int" val="40"/>
      <sval type="int" val="4"/>
    </sval>
    <sval type="array" size="2">
      <sval type="int" val="40"/>
      <sval type="int" val="2"/>
    </sval>
    <sval type="array" size="2">
      <sval type="int" val="41"/>
      <sval type="int" val="2"/>
    </sval>
    <sval type="array" size="3">
      <sval type="int" val="41"/>
      <sval type="int" val="1"/>
      <sval type="string" val="--------------------------------------------------------------------------------"/>
    </sval>
    <sval type="array" size="2">
      <sval type="int" val="42"/>
      <sval type="int" val="2"/>
    </sval>
    <sval type="array" size="2">
      <sval type="int" val="45"/>
      <sval type="int" val="2"/>
    </sval>
    <sval type="array" size="3">
      <sval type="int" val="45"/>
      <sval type="int" val="1"/>
      <sval type="string" val="Find the ware"/>
    </sval>
    <sval type="array" size="2">
      <sval type="int" val="47"/>
      <sval type="int" val="2"/>
    </sval>
    <sval type="array" size="2">
      <sval type="int" val="48"/>
      <sval type="int" val="2"/>
    </sval>
    <sval type="array" size="2">
      <sval type="int" val="49"/>
      <sval type="int" val="2"/>
    </sval>
    <sval type="array" size="2">
      <sval type="int" val="51"/>
      <sval type="int" val="2"/>
    </sval>
    <sval type="array" size="2">
      <sval type="int" val="55"/>
      <sval type="int" val="7"/>
    </sval>
    <sval type="array" size="2">
      <sval type="int" val="55"/>
      <sval type="int" val="4"/>
    </sval>
    <sval type="array" size="2">
      <sval type="int" val="55"/>
      <sval type="int" val="2"/>
    </sval>
    <sval type="array" size="3">
      <sval type="int" val="55"/>
      <sval type="int" val="1"/>
      <sval type="string" val="end if ware.props"/>
    </sval>
    <sval type="array" size="2">
      <sval type="int" val="55"/>
      <sval type="int" val="4"/>
    </sval>
    <sval type="array" size="2">
      <sval type="int" val="55"/>
      <sval type="int" val="2"/>
    </sval>
    <sval type="array" size="3">
      <sval type="int" val="56"/>
      <sval type="int" val="1"/>
      <sval type="string" val="end while index"/>
    </sval>
    <sval type="array" size="2">
      <sval type="int" val="57"/>
      <sval type="int" val="4"/>
    </sval>
    <sval type="array" size="2">
      <sval type="int" val="57"/>
      <sval type="int" val="2"/>
    </sval>
    <sval type="array" size="2">
      <sval type="int" val="58"/>
      <sval type="int" val="2"/>
    </sval>
    <sval type="array" size="3">
      <sval type="int" val="58"/>
      <sval type="int" val="1"/>
      <sval type="string" val="--------------------------------------------------------------------------------"/>
    </sval>
    <sval type="array" size="2">
      <sval type="int" val="59"/>
      <sval type="int" val="2"/>
    </sval>
    <sval type="array" size="2">
      <sval type="int" val="63"/>
      <sval type="int" val="2"/>
    </sval>
    <sval type="array" size="2">
      <sval type="int" val="65"/>
      <sval type="int" val="2"/>
    </sval>
  </sval>
  <sval type="int" val="0"/>
</sval>

</codearray>
</script>
